[
  {
    "medicationId": "21",
    "profileId": "10",
    "physicianId": "1",
    "dosage": "500 mg orally 3 times a day for 14 to 28 days",
    "name": "Amoxicillin",
    "refillExpireDate": 1626359541000
  },
  {
    "medicationId": "22",
    "profileId": "11",
    "physicianId": "2",
    "dosage": "200 mg orally every 4 hours as needed",
    "name": "Ibuprofen",
    "refillExpireDate": 1625238122000
  },
  {
    "medicationId": "250c9b08-13ca-438a-956e-e93805e7668a",
    "physicianId": "1",
    "profileId": "10",
    "name": "Levothyroxine",
    "dosage": "100 mg orally 3 times a day for 10 to 12 days",
    "refillExpireDate": 1626359541000
  },
  {
    "medicationId": "890692a5-80d6-4330-a507-d82b8b911c86",
    "physicianId": "2",
    "profileId": "a7af1fe4-085b-4477-942e-fd03e0ee22ca",
    "name": "Tylenol",
    "dosage": "1 tablet every 6 hours",
    "refillExpireDate": 1642752000000
  },
  {
    "medicationId": "8009dd50-78fb-40f3-8563-d34f9ffdc567",
    "physicianId": "1",
    "profileId": "a7af1fe4-085b-4477-942e-fd03e0ee22ca",
    "name": "Levothyroxine",
    "dosage": "100 mg orally 3 times a day for 10 to 12 days",
    "refillExpireDate": 1652857200000
  },
  {
    "medicationId": "3badbd10-5ccf-4f03-91ac-cc92b5d9cdb4",
    "physicianId": "3",
    "profileId": "a7af1fe4-085b-4477-942e-fd03e0ee22ca",
    "name": "Ibuprofen",
    "dosage": "200 to 400 mg orally every 4 hours as needed",
    "refillExpireDate": 1642579200000
  },
  {
    "medicationId": "c55040cb-64bd-400e-b34a-a3e643dee8f1",
    "physicianId": "3",
    "profileId": "a4fd6e94-baf0-492f-8069-84a96b54395f",
    "name": "Tylenol",
    "dosage": "1 tablet every 8 hours",
    "refillExpireDate": 1645603200000
  },
  {
    "medicationId": "53515e6b-92b3-4310-a90e-c0ddc9b90a08",
    "physicianId": "4ce17e91-b1de-4ff7-ae40-339b306d5852",
    "profileId": "a7af1fe4-085b-4477-942e-fd03e0ee22ca",
    "name": "Lexapro",
    "dosage": "once daily, in the morning or evening, with or without food.",
    "refillExpireDate": 1645776000000
  },
  {
    "medicationId": "fcafefdf-b4d0-4b72-b2f1-d14ed56f42af",
    "physicianId": "3",
    "profileId": "a7af1fe4-085b-4477-942e-fd03e0ee22ca",
    "name": "Metformin",
    "dosage": "Take only once daily with the evening meal.",
    "refillExpireDate": 1643702400000
  },
  {
    "medicationId": "bcb7975c-709c-42c6-b3f3-175d71344bc5",
    "physicianId": "3",
    "profileId": "a7af1fe4-085b-4477-942e-fd03e0ee22ca",
    "name": "Losartan",
    "dosage": "Take 50 mg orally once a day.",
    "refillExpireDate": 1669363200000
  },
  {
    "medicationId": "68ba968c-3324-4586-bbb3-0757cca1ccf8",
    "physicianId": "584bdfd0-4c66-4109-90da-237f50e5f987",
    "profileId": "4a418078-7585-4cf1-be60-b01db095249d",
    "name": "Tylenol",
    "dosage": "1 tablet every 6 hours",
    "refillExpireDate": 1707206400000
  }
]